{"stats":{"minecraft:dropped":{"minecraft:filled_map":1,"minecraft:grass_block":1},"minecraft:crafted":{"minecraft:filled_map":15},"minecraft:custom":{"minecraft:open_chest":7,"minecraft:time_since_rest":8902,"minecraft:play_one_minute":31930,"minecraft:deaths":1,"minecraft:sprint_one_cm":44968,"minecraft:damage_taken":285,"minecraft:walk_one_cm":110640,"minecraft:sneak_time":69,"minecraft:walk_under_water_one_cm":1456,"minecraft:drop":2,"minecraft:jump":267,"minecraft:damage_dealt":50,"minecraft:leave_game":8,"minecraft:walk_on_water_one_cm":3543,"minecraft:time_since_death":8836,"minecraft:climb_one_cm":1461,"minecraft:fall_one_cm":4843,"minecraft:fly_one_cm":151175},"minecraft:mined":{"minecraft:oak_log":5,"minecraft:oak_leaves":22},"minecraft:picked_up":{"minecraft:item_frame":1,"minecraft:wheat_seeds":1,"minecraft:torch":3,"minecraft:filled_map":16,"minecraft:oak_log":5,"minecraft:oak_sapling":2,"minecraft:birch_sapling":6,"minecraft:egg":7},"minecraft:used":{"minecraft:item_frame":1,"minecraft:torch":3,"minecraft:oak_sapling":2,"minecraft:grass_block":52,"minecraft:map":2,"minecraft:egg":1}},"DataVersion":1952}